[
  {
    "key": "0-place",
    "original": "외곽 너머",
    "context": "EN :\nOutreaches of the Outskirts\nJP :\n外郭の彼方"
  },
  {
    "key": "0-teller",
    "original": "이름 모를 소년",
    "context": "EN :\nUnknown Boy\nJP :\n名も知らぬ少年"
  },
  {
    "key": "0-title",
    "original": "???",
    "context": "EN :\n???\nJP :\n???"
  },
  {
    "key": "0-content",
    "original": "우와, 고요해.",
    "context": "EN :\nIt's quiet.\nJP :\n静かだ。"
  },
  {
    "key": "1-teller",
    "original": "이름 모를 소년",
    "context": "EN :\nUnknown Boy\nJP :\n名も知らぬ少年"
  },
  {
    "key": "1-title",
    "original": "???",
    "context": "EN :\n???\nJP :\n???"
  },
  {
    "key": "1-content",
    "original": "외곽과는 너무 달라…",
    "context": "EN :\nNothing like the Outskirts...\nJP :\n外郭とはあまりにも違う…。"
  },
  {
    "key": "2-teller",
    "original": "스테파네트",
    "context": "EN :\nStephanette\nJP :\nステファネット"
  },
  {
    "key": "2-title",
    "original": "???",
    "context": "EN :\n???\nJP :\n???"
  },
  {
    "key": "2-content",
    "original": "그러게. 외곽 너머는 이렇게 아름답고 고즈넉한 것들만 존재하는 세계였어?",
    "context": "EN :\nYou're right. Was the world beyond the Outskirts one filled with such beautiful and tranquil beings?\nJP :\nそうね。外郭の彼方にはこれほどに美しく、静まりかえったものばかりが存在する世界だったのかしら？"
  },
  {
    "key": "3-teller",
    "original": "이름 모를 소년",
    "context": "EN :\nUnknown Boy\nJP :\n名も知らぬ少年"
  },
  {
    "key": "3-title",
    "original": "???",
    "context": "EN :\n???\nJP :\n???"
  },
  {
    "key": "3-content",
    "original": "응, 그래서였나 봐. 다들 쉬쉬하면서 입에 담으려 하지도 않던 이유가.",
    "context": "EN :\nYeah, I guess that must be the reason everyone tried to keep quiet about it.\nJP :\nうん、だからみたい。みんながシーって、口にしようともしなかった理由が。"
  },
  {
    "key": "4-teller",
    "original": "스테파네트",
    "context": "EN :\nStephanette\nJP :\nステファネット"
  },
  {
    "key": "4-title",
    "original": "???",
    "context": "EN :\n???\nJP :\n???"
  },
  {
    "key": "4-content",
    "original": "아, 당신 혹시… 외곽 너머에 대한 이야기를 알고 있어? 이곳에 사는 것 중 어떤 건… 간절한 사람에게 소원을 이뤄 준대. 들려줄까?",
    "context": "EN :\nRight, do you, by any chance... know a story about the things beyond the Outskirts? It's said there's a thing that lives here... granting wishes to those who are earnest. Wanna hear it?\nJP :\nあ、ところであなた…外郭の彼方についての話は知っているかしら？ここに住む、とあるものは…切実な願いを持つ人の願いを叶えてくれるらしいのよ。聞かせてあげましょうか？"
  },
  {
    "key": "5-teller",
    "original": "이름 모를 소년",
    "context": "EN :\nUnknown Boy\nJP :\n名も知らぬ少年"
  },
  {
    "key": "5-title",
    "original": "???",
    "context": "EN :\n???\nJP :\n???"
  },
  {
    "key": "5-content",
    "original": "좋아. 네가 해주는 이야기는 언제나 기대돼.",
    "context": "EN :\nSure. I always look forward to your stories.\nJP :\nいいよ。君の物語はいつであっても楽しいからね。"
  },
  {
    "key": "6-teller",
    "original": "스테파네트",
    "context": "EN :\nStephanette\nJP :\nステファネット"
  },
  {
    "key": "6-title",
    "original": "???",
    "context": "EN :\n???\nJP :\n???"
  },
  {
    "key": "6-content",
    "original": "조금만 기다려 줄래? 아까 저쪽에서 멋진 걸 봤거든.",
    "context": "EN :\nCan it wait just a moment? I saw something nice over there.\nJP :\nちょっとだけ待ってくれるかしら？さっきあそこで凄いものを見たのよね。"
  },
  {
    "key": "7-teller",
    "original": "이름 모를 소년",
    "context": "EN :\nUnknown Boy\nJP :\n名も知らぬ少年"
  },
  {
    "key": "7-title",
    "original": "???",
    "context": "EN :\n???\nJP :\n???"
  },
  {
    "key": "7-content",
    "original": "…….",
    "context": "EN :\n……\nJP :\n……。"
  },
  {
    "key": "8-teller",
    "original": "이름 모를 소년",
    "context": "EN :\nUnknown Boy\nJP :\n名も知らぬ少年"
  },
  {
    "key": "8-title",
    "original": "???",
    "context": "EN :\n???\nJP :\n???"
  },
  {
    "key": "8-content",
    "original": "우리의 하늘을 올려다보면… 보이는 건 탁해진 빛 한 줌뿐이지.",
    "context": "EN :\nWhen we look up at our sky... all we see is a pinch of muddled light.\nJP :\n僕らの空を見上げれば…見えるのはたった一筋の濁った光だけだ。"
  },
  {
    "key": "9-teller",
    "original": "이름 모를 소년",
    "context": "EN :\nUnknown Boy\nJP :\n名も知らぬ少年"
  },
  {
    "key": "9-title",
    "original": "???",
    "context": "EN :\n???\nJP :\n???"
  },
  {
    "key": "9-content",
    "original": "하지만 이곳의 하늘은…",
    "context": "EN :\nBut here...\nJP :\nでもここの空は…。"
  },
  {
    "key": "10-teller",
    "original": "이름 모를 소년",
    "context": "EN :\nUnknown Boy\nJP :\n名も知らぬ少年"
  },
  {
    "key": "10-title",
    "original": "???",
    "context": "EN :\n???\nJP :\n???"
  },
  {
    "key": "10-content",
    "original": "우리를 고독하게 내려다보고 있는 별님들이 보이네.",
    "context": "EN :\nI can see lone stars looking down at us.\nJP :\n僕らを孤独に見下ろしているお星様たちが見えるね。"
  },
  {
    "key": "11-teller",
    "original": "이름 모를 소년",
    "context": "EN :\nUnknown Boy\nJP :\n名も知らぬ少年"
  },
  {
    "key": "11-title",
    "original": "???",
    "context": "EN :\n???\nJP :\n???"
  },
  {
    "key": "11-content",
    "original": "여기서 보이는 저 도시는 고통과 절망으로 우는 소리밖에는 들리지 않으니…",
    "context": "EN :\nSince the city I can see from here is filled with cries of pain and despair...\nJP :\nここから見えるあの都市は、苦痛と絶望で泣く声しか聞こえないから…。"
  },
  {
    "key": "12-teller",
    "original": "이름 모를 소년",
    "context": "EN :\nUnknown Boy\nJP :\n名も知らぬ少年"
  },
  {
    "key": "12-title",
    "original": "???",
    "context": "EN :\n???\nJP :\n???"
  },
  {
    "key": "12-content",
    "original": "차라리… 나도 높고 쓸쓸한 곳에서 사람들을 보며 함께 눈물을 흘릴 수 있다면…",
    "context": "EN :\nI'd rather... gaze down at people from the loneliness up in the sky and shed tears with them...\nJP :\nいっそ…僕も高く寂しい場所で、人々を見て共に涙を流せたら…。"
  },
  {
    "key": "14-teller",
    "original": "스테파네트",
    "context": "EN :\nStephanette\nJP :\nステファネット"
  },
  {
    "key": "14-title",
    "original": "???",
    "context": "EN :\n???\nJP :\n???"
  },
  {
    "key": "14-content",
    "original": "미안, 조금 늦었지. 처음 보는 꽃이 피었는데 향기를 맡으며 같이 들으면…",
    "context": "EN :\nSorry, I was a bit late. There were flowers I'd never seen before, maybe we could smell them as I tell my story...\nJP :\nごめんなさいね、少し遅れてしまって。初めて見る花が咲いてたのだけど、香りを嗅ぎながら一緒に聞けば…。"
  },
  {
    "key": "15-teller",
    "original": "스테파네트",
    "context": "EN :\nStephanette\nJP :\nステファネット"
  },
  {
    "key": "15-title",
    "original": "???",
    "context": "EN :\n???\nJP :\n???"
  },
  {
    "key": "15-content",
    "original": "…….",
    "context": "EN :\n……\nJP :\n……。"
  },
  {
    "key": "16-teller",
    "original": "스테파네트",
    "context": "EN :\nStephanette\nJP :\nステファネット"
  },
  {
    "key": "16-title",
    "original": "???",
    "context": "EN :\n???\nJP :\n???"
  },
  {
    "key": "16-content",
    "original": "그래, 마침내… 소원을 이룬 거야?",
    "context": "EN :\nI see, have you... finally fulfilled your wish?\nJP :\nそう、ついに…願いを叶えたの？"
  },
  {
    "key": "17-teller",
    "original": "스테파네트",
    "context": "EN :\nStephanette\nJP :\nステファネット"
  },
  {
    "key": "17-title",
    "original": "???",
    "context": "EN :\n???\nJP :\n???"
  },
  {
    "key": "17-content",
    "original": "오늘부터, 밤하늘 귀퉁이에 별이 한 움큼 뜨지 않아도…",
    "context": "EN :\nStarting today, even if the handful of stars doesn't rise in a corner of the night sky...\nJP :\n今宵より、夜空の片隅に星が一握りも浮かばなくても…。"
  },
  {
    "key": "18-teller",
    "original": "스테파네트",
    "context": "EN :\nStephanette\nJP :\nステファネット"
  },
  {
    "key": "18-title",
    "original": "???",
    "context": "EN :\n???\nJP :\n???"
  },
  {
    "key": "18-content",
    "original": "그 별님들은 지상에서 대신 어둠을 밝히고 있으니…",
    "context": "EN :\nThose stars will light the dark of the lands below instead...\nJP :\nあのお星様たちは地上で代わりに闇を照らしているから…。"
  },
  {
    "key": "19-teller",
    "original": "스테파네트",
    "context": "EN :\nStephanette\nJP :\nステファネット"
  },
  {
    "key": "19-title",
    "original": "???",
    "context": "EN :\n???\nJP :\n???"
  },
  {
    "key": "19-content",
    "original": "그러니 괜찮을 거야.",
    "context": "EN :\nSo it'll all be okay.\nJP :\nだから大丈夫でしょう。"
  },
  {
    "key": "20-content",
    "original": "　",
    "context": "EN :\n　\nJP :\n　"
  },
  {
    "key": "21-place",
    "original": "꽃이 피던 구인회",
    "context": "EN :\nBlossoming League of Nine Littérateurs\nJP :\n花が咲いていた九人会"
  },
  {
    "key": "21-model",
    "original": "싱클레어",
    "translation": "辛克莱",
    "context": "这是当前说话人物的默认名称,仅供参考\nEN :\nSinclair\nJP :\nシンクレア"
  },
  {
    "key": "21-content",
    "original": "아까 그 장면은 뭐였죠? 아주 머나먼 이야기 같았어요.",
    "context": "EN :\nWhat was that just now? It felt like a story from long ago.\nJP :\nさっきのあの場面は何だったんですか？凄く遠い昔の話みたいでしたね。"
  },
  {
    "key": "22-model",
    "original": "파우스트",
    "translation": "浮士德",
    "context": "这是当前说话人物的默认名称,仅供参考\nEN :\nFaust\nJP :\nファウスト"
  },
  {
    "key": "22-content",
    "original": "황금가지가 폭주하면서 자아 심도를 생성할 때… 불순물이 섞여 들어왔어요.",
    "context": "EN :\nAs the Golden Bough generated the fathoms of ego in a frenzy... foreign matters were mixed into them.\nJP :\n黄金の枝が暴走しながら自我心道を生成するとき…不純物が入り交じりました。"
  },
  {
    "key": "23-model",
    "original": "파우스트",
    "translation": "浮士德",
    "context": "这是当前说话人物的默认名称,仅供参考\nEN :\nFaust\nJP :\nファウスト"
  },
  {
    "key": "23-content",
    "original": "K사의 특이점. 일명 ‘눈물 흘리는 것’의 눈물.",
    "context": "EN :\nK Corp's Singularity: Tears of the so-called 'Tearful Thing'.\nJP :\nK社の特異点。またの名を「涙を流すもの」の涙。"
  },
  {
    "key": "24-model",
    "original": "그레고르",
    "translation": "格里高尔",
    "context": "这是当前说话人物的默认名称,仅供参考\nEN :\nGregor\nJP :\nグレゴール"
  },
  {
    "key": "24-content",
    "original": "그래… 그 영향으로 죽었던 사람들까지 덤벼들고 있잖아.",
    "context": "EN :\nCan sure see that... It's bringing back dead people to fight us.\nJP :\nあぁ…その影響で死んでた人たちまで襲いかかって来てるじゃないか。"
  },
  {
    "key": "25-model",
    "original": "파우스트",
    "translation": "浮士德",
    "context": "这是当前说话人物的默认名称,仅供参考\nEN :\nFaust\nJP :\nファウスト"
  },
  {
    "key": "25-content",
    "original": "네, 그것에 대한… 녹아내려진 기억인 듯하네요.",
    "context": "EN :\nYes, they seem to be relevant to the experiences... of melting down.\nJP :\nはい、それに対する…融け落ちた記憶のようですね。"
  },
  {
    "key": "26-model",
    "original": "홍루",
    "translation": "鸿璐",
    "context": "这是当前说话人物的默认名称,仅供参考\nEN :\nHong Lu\nJP :\nホンル"
  },
  {
    "key": "26-content",
    "original": "그 눈물 흘리는 것의 마음도 이 공명에 녹아든 건가요?",
    "context": "EN :\nDid the mind of that Tearful Thing melt into this resonance as well, then?\nJP :\nあの涙を流すものの心も、この共鳴に溶け込んだんですか？"
  },
  {
    "key": "27-model",
    "original": "싱클레어",
    "translation": "辛克莱",
    "context": "这是当前说话人物的默认名称,仅供参考\nEN :\nSinclair\nJP :\nシンクレア"
  },
  {
    "key": "27-content",
    "original": "그러면… 눈물 흘리는 것도 역시…사람과 다를 바 없는…",
    "context": "EN :\nThat means... the Tearful Thing is... no different from people...\nJP :\nそれなら…涙を流すものもまた…人間とそう変わりない…。"
  },
  {
    "key": "28-model",
    "original": "파우스트",
    "translation": "浮士德",
    "context": "这是当前说话人物的默认名称,仅供参考\nEN :\nFaust\nJP :\nファウスト"
  },
  {
    "key": "28-content",
    "original": "단테, 세상에는… 별을 찾고자 하는 이들이 많아요.",
    "context": "EN :\nDante, in this world... there are many who seek after stars.\nJP :\nダンテ、この世には…星を探そうとする者が沢山います。"
  }
]